geo_mapper_api/__init__.py
geo_mapper_api/converters.py
geo_mapper_api/filters.py
geo_mapper_api/inrix_to_osm.py
geo_mapper_api-0.1.2.dist-info/METADATA
geo_mapper_api-0.1.2.dist-info/WHEEL
geo_mapper_api-0.1.2.dist-info/top_level.txt
geo_mapper_api-0.1.2.dist-info/RECORD
