Metadata-Version: 2.4
Name: geo_mapper_api
Version: 0.1.2
Summary: A simple API for matching geospatial data to OSM IDs
Author-email: JP Talusan <jptalusan@gmail.com>
Project-URL: Homepage, https://github.com/jptalusan/geospatial_mapper
Requires-Python: >=3.9
Requires-Dist: pandas<=1.4.4
Requires-Dist: geopandas<=0.12.2
Requires-Dist: numpy>=1.22.4
Requires-Dist: osmnx>=1.9.4
Requires-Dist: fiona==1.9.6
Requires-Dist: pytest
Provides-Extra: dev
Requires-Dist: pytest; extra == "dev"
